[
  {
    "session_id": 399186,
    "session_date": "12/15/2022 12:00:00 AM",
    "event_id": 771,
    "eventname": "2022 KING OF THE ICE 2022/2023",
    "speed_avg": 54.08173360000001,
    "speed_2sec": 55.472956,
    "speed_10sec": 55.008104,
    "speed_100": 55.247012000000005,
    "speed_250": 54.026544,
    "speed_500": 48.853908000000004,
    "speed_mile": 0.0,
    "speed_hour": 19.166348000000003,
    "speed_halfhour": 21.50172,
    "speed_24hour": 0.0,
    "speed_alpha_racing": 0.0,
    "session_distance": 34.095709,
    "username": "Pieter Hamstra",
    "flag": "NL",
    "sexe": "Men",
    "spotname": "Zuidlaardermeer",
    "sessionboard": "Custom Triangle,  1995",
    "sessionsail": "Duotone Warp_fin 2022 7.8,  2022",
    "sessionfin": "Custom ice blade  0",
    "sessiongpstype": "Motion",
    "sessionurl": "https://www.gps-icesailing.com/?mnu=user&val=399186&uid=90"
  },
  {
    "session_id": 399192,
    "session_date": "12/10/2022 12:00:00 AM",
    "event_id": 771,
    "eventname": "2022 KING OF THE ICE 2022/2023",
    "speed_avg": 39.8691152,
    "speed_2sec": 45.10731200000001,
    "speed_10sec": 43.059000000000005,
    "speed_100": 43.223828,
    "speed_250": 40.538428,
    "speed_500": 37.275204,
    "speed_mile": 33.411932,
    "speed_hour": 0.0,
    "speed_halfhour": 15.317892000000002,
    "speed_24hour": 0.0,
    "speed_alpha_racing": 40.860676,
    "session_distance": 8.742479999999999,
    "username": "Tommy Gustavsson",
    "flag": "SE",
    "sexe": "Men",
    "spotname": "Brunnbybaden",
    "sessionboard": "Hiberna 4 runner,  2009",
    "sessionsail": "XO-Sails Shark 4.7,  2010",
    "sessionfin": "Custom ice blade  0",
    "sessiongpstype": "Mobile Phone App",
    "sessionurl": "https://www.gps-icesailing.com/?mnu=user&val=399192&uid=24740"
  },
  {
    "session_id": 399195,
    "session_date": "12/10/2022 12:00:00 AM",
    "event_id": 771,
    "eventname": "2022 KING OF THE ICE 2022/2023",
    "speed_avg": 39.8691152,
    "speed_2sec": 45.10731200000001,
    "speed_10sec": 43.059000000000005,
    "speed_100": 43.223828,
    "speed_250": 40.538428,
    "speed_500": 37.275204,
    "speed_mile": 33.411932,
    "speed_hour": 0.0,
    "speed_halfhour": 15.317892000000002,
    "speed_24hour": 0.0,
    "speed_alpha_racing": 40.860676,
    "session_distance": 8.742479999999999,
    "username": "Tommy Gustavsson",
    "flag": "SE",
    "sexe": "Men",
    "spotname": "Brunnbybaden",
    "sessionboard": "Hiberna 4 runner,  2009",
    "sessionsail": "XO-Sails Shark 4.7,  2010",
    "sessionfin": "Custom ice blade  0",
    "sessiongpstype": "Mobile Phone App",
    "sessionurl": "https://www.gps-icesailing.com/?mnu=user&val=399195&uid=24740"
  },
  {
    "session_id": 399211,
    "session_date": "12/17/2022 12:00:00 AM",
    "event_id": 771,
    "eventname": "2022 KING OF THE ICE 2022/2023",
    "speed_avg": 59.01842480000001,
    "speed_2sec": 64.5885,
    "speed_10sec": 63.451372000000006,
    "speed_100": 64.08475600000001,
    "speed_250": 63.018004000000005,
    "speed_500": 60.710412,
    "speed_mile": 0.0,
    "speed_hour": 18.555188,
    "speed_halfhour": 26.639168,
    "speed_24hour": 0.0,
    "speed_alpha_racing": 0.0,
    "session_distance": 44.294775,
    "username": "Pieter Hamstra",
    "flag": "NL",
    "sexe": "Men",
    "spotname": "Zuidlaardermeer",
    "sessionboard": "Custom Triangle,  1995",
    "sessionsail": "Duotone Warp 20.20 7.0,  2020",
    "sessionfin": "Custom ice blade  0",
    "sessiongpstype": "Motion",
    "sessionurl": "https://www.gps-icesailing.com/?mnu=user&val=399211&uid=90"
  },
  {
    "session_id": 399214,
    "session_date": "12/17/2022 12:00:00 AM",
    "event_id": 771,
    "eventname": "2022 KING OF THE ICE 2022/2023",
    "speed_avg": 52.46716000000001,
    "speed_2sec": 54.43954,
    "speed_10sec": 54.372868000000004,
    "speed_100": 54.43954,
    "speed_250": 53.919128,
    "speed_500": 52.459752,
    "speed_mile": 44.11464,
    "speed_hour": 21.449864,
    "speed_halfhour": 30.848764000000003,
    "speed_24hour": 0.0,
    "speed_alpha_racing": 25.787248,
    "session_distance": 49.244103,
    "username": "Nils Duindam",
    "flag": "NL",
    "sexe": "Men",
    "spotname": "Veluwemeer - Nunspeet/Polsmaten",
    "sessionboard": "Custom Triangle,  2022",
    "sessionsail": "Phantom IRIS R mk2 6.5,  2022",
    "sessionfin": "Custom ice blade  0",
    "sessiongpstype": "COROS APEX PRO",
    "sessionurl": "https://www.gps-icesailing.com/?mnu=user&val=399214&uid=4058"
  },
  {
    "session_id": 399215,
    "session_date": "12/17/2022 12:00:00 AM",
    "event_id": 771,
    "eventname": "2022 KING OF THE ICE 2022/2023",
    "speed_avg": 45.8281104,
    "speed_2sec": 49.629896,
    "speed_10sec": 47.82604800000001,
    "speed_100": 48.470544000000004,
    "speed_250": 46.164804000000004,
    "speed_500": 45.140648,
    "speed_mile": 0.0,
    "speed_hour": 17.479176000000002,
    "speed_halfhour": 18.925588,
    "speed_24hour": 0.0,
    "speed_alpha_racing": 0.0,
    "session_distance": 34.155027000000004,
    "username": "John Overmeer",
    "flag": "NL",
    "sexe": "Men",
    "spotname": "Veluwemeer - Nunspeet/Polsmaten",
    "sessionboard": "Custom  JB Iceboard,  2017",
    "sessionsail": "Loftsails oxygen 5.8,  2018",
    "sessionfin": "Custom ice blade  0",
    "sessiongpstype": "COROS APEX PRO",
    "sessionurl": "https://www.gps-icesailing.com/?mnu=user&val=399215&uid=102"
  },
  {
    "session_id": 399216,
    "session_date": "12/17/2022 12:00:00 AM",
    "event_id": 771,
    "eventname": "2022 KING OF THE ICE 2022/2023",
    "speed_avg": 56.6389752,
    "speed_2sec": 59.59736,
    "speed_10sec": 58.743588,
    "speed_100": 59.112136,
    "speed_250": 58.056496,
    "speed_500": 56.77861600000001,
    "speed_mile": 47.63158800000001,
    "speed_hour": 27.820744,
    "speed_halfhour": 28.667108,
    "speed_24hour": 0.0,
    "speed_alpha_racing": 29.42828,
    "session_distance": 70.47796000000001,
    "username": "Robert Seinen",
    "flag": "NL",
    "sexe": "Men",
    "spotname": "Veluwemeer - Nunspeet/Polsmaten",
    "sessionboard": "Custom 3 Hoek ,  2010",
    "sessionsail": "S2 Maui Venom 6.1,  2022",
    "sessionfin": "Custom ice blade  0",
    "sessiongpstype": "Locosys GW-60",
    "sessionurl": "https://www.gps-icesailing.com/?mnu=user&val=399216&uid=994"
  },
  {
    "session_id": 399238,
    "session_date": "12/18/2022 12:00:00 AM",
    "event_id": 771,
    "eventname": "2022 KING OF THE ICE 2022/2023",
    "speed_avg": 22.4306832,
    "speed_2sec": 23.994512,
    "speed_10sec": 23.496324,
    "speed_100": 23.203708000000002,
    "speed_250": 22.085100000000004,
    "speed_500": 17.005064,
    "speed_mile": 0.0,
    "speed_hour": 5.957884000000001,
    "speed_halfhour": 7.320956,
    "speed_24hour": 0.0,
    "speed_alpha_racing": 0.0,
    "session_distance": 11.770209999999999,
    "username": "Nicole Skodda",
    "flag": "DE",
    "sexe": "Woman",
    "spotname": "Veluwemeer - Nunspeet/Polsmaten",
    "sessionboard": "Pirate Pirate,  2011",
    "sessionsail": "Loftsails Pure Lip 5.0,  2014",
    "sessionfin": "Custom ice blade  0",
    "sessiongpstype": "Locosys GT-31",
    "sessionurl": "https://www.gps-icesailing.com/?mnu=user&val=399238&uid=6348"
  },
  {
    "session_id": 399244,
    "session_date": "12/18/2022 12:00:00 AM",
    "event_id": 771,
    "eventname": "2022 KING OF THE ICE 2022/2023",
    "speed_avg": 57.17235120000001,
    "speed_2sec": 59.410308,
    "speed_10sec": 57.991676,
    "speed_100": 58.626912,
    "speed_250": 57.306436000000005,
    "speed_500": 57.054564,
    "speed_mile": 46.3926,
    "speed_hour": 29.117144,
    "speed_halfhour": 36.597372,
    "speed_24hour": 0.0,
    "speed_alpha_racing": 42.194116,
    "session_distance": 71.28105599999999,
    "username": "Adam Mr\u00f3z",
    "flag": "PL",
    "sexe": "Men",
    "spotname": "Jamno",
    "sessionboard": "- Iceboard Mroz,  2020",
    "sessionsail": "Loftsails Racingblade 6.3,  2022",
    "sessionfin": "Custom ice blade  0",
    "sessiongpstype": "Locosys GW-60",
    "sessionurl": "https://www.gps-icesailing.com/?mnu=user&val=399244&uid=18026"
  },
  {
    "session_id": 399251,
    "session_date": "12/18/2022 12:00:00 AM",
    "event_id": 771,
    "eventname": "2022 KING OF THE ICE 2022/2023",
    "speed_avg": 38.76236,
    "speed_2sec": 42.220044,
    "speed_10sec": 41.369976,
    "speed_100": 41.54036,
    "speed_250": 38.48456,
    "speed_500": 36.29364400000001,
    "speed_mile": 0.0,
    "speed_hour": 7.1227920000000005,
    "speed_halfhour": 13.617756,
    "speed_24hour": 0.0,
    "speed_alpha_racing": 0.0,
    "session_distance": 17.172207,
    "username": "John Overmeer",
    "flag": "NL",
    "sexe": "Men",
    "spotname": "Veluwemeer - Nunspeet/Polsmaten",
    "sessionboard": "Custom  JB Iceboard,  2017",
    "sessionsail": "Point-7 ACX 4.7,  2021",
    "sessionfin": "Custom ice blade  0",
    "sessiongpstype": "COROS APEX PRO",
    "sessionurl": "https://www.gps-icesailing.com/?mnu=user&val=399251&uid=102"
  },
  {
    "session_id": 399260,
    "session_date": "12/18/2022 12:00:00 AM",
    "event_id": 771,
    "eventname": "2022 KING OF THE ICE 2022/2023",
    "speed_avg": 52.901268800000004,
    "speed_2sec": 54.432132,
    "speed_10sec": 53.482056,
    "speed_100": 53.702444,
    "speed_250": 52.072684,
    "speed_500": 50.709612,
    "speed_mile": 46.381488000000004,
    "speed_hour": 33.919380000000004,
    "speed_halfhour": 35.98436,
    "speed_24hour": 0.0,
    "speed_alpha_racing": 31.513631999999998,
    "session_distance": 82.56576,
    "username": "Robert Seinen",
    "flag": "NL",
    "sexe": "Men",
    "spotname": "Veluwemeer - Nunspeet/Polsmaten",
    "sessionboard": "Custom 3 Hoek ,  2010",
    "sessionsail": "S2 Maui Venom 6.1,  2022",
    "sessionfin": "Custom ice blade  0",
    "sessiongpstype": "Locosys GT-31",
    "sessionurl": "https://www.gps-icesailing.com/?mnu=user&val=399260&uid=994"
  },
  {
    "session_id": 399261,
    "session_date": "12/18/2022 12:00:00 AM",
    "event_id": 771,
    "eventname": "2022 KING OF THE ICE 2022/2023",
    "speed_avg": 44.869885599999996,
    "speed_2sec": 47.53158,
    "speed_10sec": 46.324076000000005,
    "speed_100": 46.712996,
    "speed_250": 44.961004,
    "speed_500": 41.527395999999996,
    "speed_mile": 34.893532,
    "speed_hour": 0.0,
    "speed_halfhour": 24.442696,
    "speed_24hour": 0.0,
    "speed_alpha_racing": 35.321344,
    "session_distance": 12.222087,
    "username": "Jakub Salek",
    "flag": "PL",
    "sexe": "Men",
    "spotname": "Duze Jezioro Znin",
    "sessionboard": "Custom  Slalom Mroz 4,  2017",
    "sessionsail": "Severne Mach2 6.2,  2019",
    "sessionfin": "Custom ice blade  0",
    "sessiongpstype": "Motion",
    "sessionurl": "https://www.gps-icesailing.com/?mnu=user&val=399261&uid=25179"
  },
  {
    "session_id": 399270,
    "session_date": "12/19/2022 12:00:00 AM",
    "event_id": 771,
    "eventname": "2022 KING OF THE ICE 2022/2023",
    "speed_avg": 79.526732,
    "speed_2sec": 82.860332,
    "speed_10sec": 79.78601200000001,
    "speed_100": 82.04545200000001,
    "speed_250": 79.51562000000001,
    "speed_500": 77.952532,
    "speed_mile": 69.242576,
    "speed_hour": 51.161500000000004,
    "speed_halfhour": 57.247172000000006,
    "speed_24hour": 0.0,
    "speed_alpha_racing": 51.209652000000006,
    "session_distance": 165.544501,
    "username": "Jakub Salek",
    "flag": "PL",
    "sexe": "Men",
    "spotname": "Jamno",
    "sessionboard": "Custom  Slalom Mroz 4,  2017",
    "sessionsail": "Severne Mach3 5.5,  2020",
    "sessionfin": "Custom ice blade  0",
    "sessiongpstype": "Motion",
    "sessionurl": "https://www.gps-icesailing.com/?mnu=user&val=399270&uid=25179"
  },
  {
    "session_id": 399282,
    "session_date": "12/19/2022 12:00:00 AM",
    "event_id": 771,
    "eventname": "2022 KING OF THE ICE 2022/2023",
    "speed_avg": 80.38272640000001,
    "speed_2sec": 84.09931999999999,
    "speed_10sec": 82.33251200000001,
    "speed_100": 83.769664,
    "speed_250": 82.082492,
    "speed_500": 79.80453200000001,
    "speed_mile": 66.544212,
    "speed_hour": 41.466280000000005,
    "speed_halfhour": 45.62402000000001,
    "speed_24hour": 0.0,
    "speed_alpha_racing": 52.750516000000005,
    "session_distance": 133.16334799999998,
    "username": "Kamil Tyniewicki",
    "flag": "PL",
    "sexe": "Men",
    "spotname": "Jamno",
    "sessionboard": "Custom Iceboard,  2018",
    "sessionsail": "Point-7 AC-One 5.6,  2021",
    "sessionfin": "Custom ice blade  0",
    "sessiongpstype": "Motion",
    "sessionurl": "https://www.gps-icesailing.com/?mnu=user&val=399282&uid=23164"
  },
  {
    "session_id": 399295,
    "session_date": "12/19/2022 12:00:00 AM",
    "event_id": 771,
    "eventname": "2022 KING OF THE ICE 2022/2023",
    "speed_avg": 85.39646079999999,
    "speed_2sec": 88.564492,
    "speed_10sec": 87.566264,
    "speed_100": 87.907032,
    "speed_250": 87.542188,
    "speed_500": 85.35312400000001,
    "speed_mile": 69.20553600000001,
    "speed_hour": 45.129536,
    "speed_halfhour": 49.631748,
    "speed_24hour": 0.0,
    "speed_alpha_racing": 54.502508,
    "session_distance": 151.012338,
    "username": "Adam Mr\u00f3z",
    "flag": "PL",
    "sexe": "Men",
    "spotname": "Jamno",
    "sessionboard": "- Iceboard Mroz,  2020",
    "sessionsail": "Loftsails Ice Speed Blade 4.2,  2021",
    "sessionfin": "Custom ice blade  0",
    "sessiongpstype": "Locosys GW-60",
    "sessionurl": "https://www.gps-icesailing.com/?mnu=user&val=399295&uid=18026"
  },
  {
    "session_id": 399518,
    "session_date": "12/27/2022 12:00:00 AM",
    "event_id": 771,
    "eventname": "2022 KING OF THE ICE 2022/2023",
    "speed_avg": 73.3362368,
    "speed_2sec": 75.211572,
    "speed_10sec": 74.46892000000001,
    "speed_100": 74.86895200000001,
    "speed_250": 74.007772,
    "speed_500": 70.124128,
    "speed_mile": 60.515952000000006,
    "speed_hour": 51.400408000000006,
    "speed_halfhour": 52.307888000000005,
    "speed_24hour": 0.0,
    "speed_alpha_racing": 52.839412,
    "session_distance": 111.1402,
    "username": "Adam Mr\u00f3z",
    "flag": "PL",
    "sexe": "Men",
    "spotname": "Ewingi",
    "sessionboard": "- Iceboard Mroz,  2020",
    "sessionsail": "Loftsails Ice Speed Blade 4.2,  2021",
    "sessionfin": "Custom ice blade  0",
    "sessiongpstype": "Locosys GW-60",
    "sessionurl": "https://www.gps-icesailing.com/?mnu=user&val=399518&uid=18026"
  },
  {
    "session_id": 399529,
    "session_date": "12/26/2022 12:00:00 AM",
    "event_id": 771,
    "eventname": "2022 KING OF THE ICE 2022/2023",
    "speed_avg": 55.5800016,
    "speed_2sec": 61.793832,
    "speed_10sec": 56.811952,
    "speed_100": 58.41208,
    "speed_250": 54.535844000000004,
    "speed_500": 50.67072,
    "speed_mile": 37.936368,
    "speed_hour": 19.697872,
    "speed_halfhour": 22.322156000000003,
    "speed_24hour": 0.0,
    "speed_alpha_racing": 42.810832000000005,
    "session_distance": 78.51204,
    "username": "Tobias Bodin",
    "flag": "SE",
    "sexe": "Men",
    "spotname": "Altasjon, Stockholm",
    "sessionboard": "Custom Sharp4,  2012",
    "sessionsail": "Loftsails Purelip 5.0,  2016",
    "sessionfin": "Custom ice blade  0",
    "sessiongpstype": "Locosys GT-31",
    "sessionurl": "https://www.gps-icesailing.com/?mnu=user&val=399529&uid=5893"
  },
  {
    "session_id": 399816,
    "session_date": "12/31/2022 12:00:00 AM",
    "event_id": 771,
    "eventname": "2022 KING OF THE ICE 2022/2023",
    "speed_avg": 71.5160912,
    "speed_2sec": 77.202472,
    "speed_10sec": 74.463364,
    "speed_100": 76.06719600000001,
    "speed_250": 73.539216,
    "speed_500": 66.96091200000001,
    "speed_mile": 52.507904,
    "speed_hour": 0.0,
    "speed_halfhour": 44.929520000000004,
    "speed_24hour": 0.0,
    "speed_alpha_racing": 48.409428,
    "session_distance": 32.990190000000005,
    "username": "Henrik M\u00e5rd",
    "flag": "SE",
    "sexe": "Men",
    "spotname": "Drevviken",
    "sessionboard": "Custom M\u00e5rdboard 4.1,  2016",
    "sessionsail": "Neilpryde RS Racing EVO 2 7.0,  2009",
    "sessionfin": "Custom ice blade  0",
    "sessiongpstype": "Locosys GW-60",
    "sessionurl": "https://www.gps-icesailing.com/?mnu=user&val=399816&uid=1468"
  },
  {
    "session_id": 399855,
    "session_date": "12/31/2022 12:00:00 AM",
    "event_id": 771,
    "eventname": "2022 KING OF THE ICE 2022/2023",
    "speed_avg": 61.79494320000001,
    "speed_2sec": 67.446136,
    "speed_10sec": 65.188548,
    "speed_100": 66.786824,
    "speed_250": 64.353296,
    "speed_500": 60.11592,
    "speed_mile": 21.56654,
    "speed_hour": 13.936300000000001,
    "speed_halfhour": 14.828964000000001,
    "speed_24hour": 0.0,
    "speed_alpha_racing": 19.136716,
    "session_distance": 23.40241,
    "username": "Valde Viiding",
    "flag": "EE",
    "sexe": "Men",
    "spotname": "H\u00e4\u00e4demeeste",
    "sessionboard": "not defined ,  0",
    "sessionsail": "not defined  0.0,  0",
    "sessionfin": "Custom ice blade  0",
    "sessiongpstype": "Locosys GT-31",
    "sessionurl": "https://www.gps-icesailing.com/?mnu=user&val=399855&uid=21996"
  },
  {
    "session_id": 399966,
    "session_date": "12/31/2022 12:00:00 AM",
    "event_id": 771,
    "eventname": "2022 KING OF THE ICE 2022/2023",
    "speed_avg": 51.5722736,
    "speed_2sec": 57.456448,
    "speed_10sec": 53.998764,
    "speed_100": 55.202564,
    "speed_250": 51.570792000000004,
    "speed_500": 46.199992,
    "speed_mile": 38.390108,
    "speed_hour": 27.033644,
    "speed_halfhour": 31.524744,
    "speed_24hour": 0.0,
    "speed_alpha_racing": 39.717992,
    "session_distance": 77.68322,
    "username": "Tobias Bodin",
    "flag": "SE",
    "sexe": "Men",
    "spotname": "Altasjon, Stockholm",
    "sessionboard": "Custom Sharp4,  2012",
    "sessionsail": "Loftsails PureLip 4.7,  2021",
    "sessionfin": "Custom ice blade  0",
    "sessiongpstype": "Locosys GT-31",
    "sessionurl": "https://www.gps-icesailing.com/?mnu=user&val=399966&uid=5893"
  },
  {
    "session_id": 400300,
    "session_date": "1/5/2023 12:00:00 AM",
    "event_id": 771,
    "eventname": "2022 KING OF THE ICE 2022/2023",
    "speed_avg": 37.31483680000001,
    "speed_2sec": 40.338412,
    "speed_10sec": 39.267956,
    "speed_100": 39.2624,
    "speed_250": 36.514032,
    "speed_500": 34.986132,
    "speed_mile": 30.435768000000003,
    "speed_hour": 0.0,
    "speed_halfhour": 14.940084,
    "speed_24hour": 0.0,
    "speed_alpha_racing": 34.945388,
    "session_distance": 7.9864,
    "username": "Thomas Barr\u00e9",
    "flag": "SE",
    "sexe": "Men",
    "spotname": "Vallentunasj\u00f6n",
    "sessionboard": "not defined ,  0",
    "sessionsail": "Goya Mark 2 6.6,  2019",
    "sessionfin": "Custom ice blade  0",
    "sessiongpstype": "Garmin forerunner935",
    "sessionurl": "https://www.gps-icesailing.com/?mnu=user&val=400300&uid=24627"
  },
  {
    "session_id": 400340,
    "session_date": "1/4/2023 12:00:00 AM",
    "event_id": 771,
    "eventname": "2022 KING OF THE ICE 2022/2023",
    "speed_avg": 49.78842720000001,
    "speed_2sec": 53.139436,
    "speed_10sec": 50.276244,
    "speed_100": 50.687388,
    "speed_250": 49.31876,
    "speed_500": 48.064956,
    "speed_mile": 39.997644,
    "speed_hour": 34.143472,
    "speed_halfhour": 34.834268,
    "speed_24hour": 0.0,
    "speed_alpha_racing": 33.986052,
    "session_distance": 60.328328,
    "username": "Giedrius Liutkus",
    "flag": "LT",
    "sexe": "Men",
    "spotname": "Kauno Marios",
    "sessionboard": "PATRIK Foil Comp 91 V2,  2021",
    "sessionsail": "S2 Maui Venom 7.0,  2020",
    "sessionfin": "Custom ice blade  0",
    "sessiongpstype": "Garmin forerunner935",
    "sessionurl": "https://www.gps-icesailing.com/?mnu=user&val=400340&uid=4506"
  },
  {
    "session_id": 400623,
    "session_date": "1/11/2023 12:00:00 AM",
    "event_id": 771,
    "eventname": "2022 KING OF THE ICE 2022/2023",
    "speed_avg": 87.9418496,
    "speed_2sec": 91.82956800000001,
    "speed_10sec": 90.501684,
    "speed_100": 91.685112,
    "speed_250": 90.501684,
    "speed_500": 89.2201,
    "speed_mile": 84.760484,
    "speed_hour": 29.269008000000003,
    "speed_halfhour": 31.965520000000005,
    "speed_24hour": 0.0,
    "speed_alpha_racing": 29.843128000000004,
    "session_distance": 44.549521999999996,
    "username": "Boris Ljubt\u0161enko",
    "flag": "EE",
    "sexe": "Men",
    "spotname": "Sarve",
    "sessionboard": "Custom Ice Sled-Al board Custom,  2022",
    "sessionsail": "Neilpryde RS3 5.8,  2003",
    "sessionfin": "Custom ice blade  0",
    "sessiongpstype": "Locosys GW-60",
    "sessionurl": "https://www.gps-icesailing.com/?mnu=user&val=400623&uid=26037"
  },
  {
    "session_id": 400652,
    "session_date": "12/31/2022 12:00:00 AM",
    "event_id": 771,
    "eventname": "2022 KING OF THE ICE 2022/2023",
    "speed_avg": 56.8349168,
    "speed_2sec": 59.873308,
    "speed_10sec": 58.33985200000001,
    "speed_100": 58.813964000000006,
    "speed_250": 57.27310000000001,
    "speed_500": 54.561772,
    "speed_mile": 42.54044,
    "speed_hour": 15.116024000000003,
    "speed_halfhour": 23.290752,
    "speed_24hour": 0.0,
    "speed_alpha_racing": 31.158048000000004,
    "session_distance": 31.813223,
    "username": "Raido Ruse",
    "flag": "EE",
    "sexe": "Men",
    "spotname": "Kahala j\u00e4rv",
    "sessionboard": "not defined ,  0",
    "sessionsail": "Cabrinha Wing 6.0,  2021",
    "sessionfin": "Custom ice blade  0",
    "sessiongpstype": "unknown",
    "sessionurl": "https://www.gps-icesailing.com/?mnu=user&val=400652&uid=26620"
  },
  {
    "session_id": 400653,
    "session_date": "1/7/2023 12:00:00 AM",
    "event_id": 771,
    "eventname": "2022 KING OF THE ICE 2022/2023",
    "speed_avg": 51.42522480000001,
    "speed_2sec": 62.408696000000006,
    "speed_10sec": 61.66234000000001,
    "speed_100": 61.6716,
    "speed_250": 61.482696000000004,
    "speed_500": 60.451132,
    "speed_mile": 47.913092,
    "speed_hour": 16.271672,
    "speed_halfhour": 17.790312,
    "speed_24hour": 0.0,
    "speed_alpha_racing": 25.03904,
    "session_distance": 20.674036,
    "username": "Raido Ruse",
    "flag": "EE",
    "sexe": "Men",
    "spotname": "P\u00e4rnu rand",
    "sessionboard": "not defined ,  0",
    "sessionsail": "Ensis WiNG 5.2,  2023",
    "sessionfin": "Custom ice blade  0",
    "sessiongpstype": "COROS APEX PRO",
    "sessionurl": "https://www.gps-icesailing.com/?mnu=user&val=400653&uid=26620"
  },
  {
    "session_id": 400824,
    "session_date": "1/14/2023 12:00:00 AM",
    "event_id": 771,
    "eventname": "2022 KING OF THE ICE 2022/2023",
    "speed_avg": 65.938608,
    "speed_2sec": 68.525852,
    "speed_10sec": 67.87765200000001,
    "speed_100": 68.368432,
    "speed_250": 67.518364,
    "speed_500": 65.02742400000001,
    "speed_mile": 51.22632,
    "speed_hour": 32.528528,
    "speed_halfhour": 37.23075600000001,
    "speed_24hour": 0.0,
    "speed_alpha_racing": 48.489064,
    "session_distance": 49.64079,
    "username": "Adam Mr\u00f3z",
    "flag": "PL",
    "sexe": "Men",
    "spotname": "V\u00f5rtsj\u00e4rv",
    "sessionboard": "- Iceboard Mroz,  2020",
    "sessionsail": "Loftsails Ice Speed Blade 4.6,  2020",
    "sessionfin": "Custom ice blade  0",
    "sessiongpstype": "Locosys GW-60",
    "sessionurl": "https://www.gps-icesailing.com/?mnu=user&val=400824&uid=18026"
  },
  {
    "session_id": 400917,
    "session_date": "1/15/2023 12:00:00 AM",
    "event_id": 771,
    "eventname": "2022 KING OF THE ICE 2022/2023",
    "speed_avg": 85.5164704,
    "speed_2sec": 90.929496,
    "speed_10sec": 87.90518000000002,
    "speed_100": 90.41464,
    "speed_250": 87.808876,
    "speed_500": 83.338148,
    "speed_mile": 49.765092,
    "speed_hour": 0.0,
    "speed_halfhour": 32.0396,
    "speed_24hour": 0.0,
    "speed_alpha_racing": 39.386484,
    "session_distance": 16.03326,
    "username": "Adam Mr\u00f3z",
    "flag": "PL",
    "sexe": "Men",
    "spotname": "V\u00f5rtsj\u00e4rv",
    "sessionboard": "- Iceboard Mroz,  2020",
    "sessionsail": "Loftsails Ice Speed Blade 4.2,  2021",
    "sessionfin": "Custom ice blade  0",
    "sessiongpstype": "Locosys GW-60",
    "sessionurl": "https://www.gps-icesailing.com/?mnu=user&val=400917&uid=18026"
  },
  {
    "session_id": 400971,
    "session_date": "1/15/2023 12:00:00 AM",
    "event_id": 771,
    "eventname": "2022 KING OF THE ICE 2022/2023",
    "speed_avg": 53.26759439999999,
    "speed_2sec": 61.382688,
    "speed_10sec": 58.4769,
    "speed_100": 59.54365200000001,
    "speed_250": 55.748904,
    "speed_500": 45.668468,
    "speed_mile": 38.77162,
    "speed_hour": 0.0,
    "speed_halfhour": 27.922604,
    "speed_24hour": 0.0,
    "speed_alpha_racing": 40.603248,
    "session_distance": 20.076489000000002,
    "username": "Thomas Barr\u00e9",
    "flag": "SE",
    "sexe": "Men",
    "spotname": "Vallentunasj\u00f6n",
    "sessionboard": "not defined ,  0",
    "sessionsail": "Neilpryde Combat 5.3,  2008",
    "sessionfin": "Custom ice blade  0",
    "sessiongpstype": "Garmin forerunner935",
    "sessionurl": "https://www.gps-icesailing.com/?mnu=user&val=400971&uid=24627"
  },
  {
    "session_id": 400975,
    "session_date": "1/15/2023 12:00:00 AM",
    "event_id": 771,
    "eventname": "2022 KING OF THE ICE 2022/2023",
    "speed_avg": 41.750747200000006,
    "speed_2sec": 45.977752,
    "speed_10sec": 44.164644,
    "speed_100": 44.425776,
    "speed_250": 41.338492,
    "speed_500": 35.397276,
    "speed_mile": 28.765264000000002,
    "speed_hour": 0.0,
    "speed_halfhour": 13.269580000000001,
    "speed_24hour": 0.0,
    "speed_alpha_racing": 36.286236,
    "session_distance": 9.785692999999998,
    "username": "Thomas Barr\u00e9",
    "flag": "SE",
    "sexe": "Men",
    "spotname": "Vallentunasj\u00f6n",
    "sessionboard": "not defined ,  0",
    "sessionsail": "Goya Mark 2 6.6,  2019",
    "sessionfin": "Custom ice blade  0",
    "sessiongpstype": "Garmin forerunner935",
    "sessionurl": "https://www.gps-icesailing.com/?mnu=user&val=400975&uid=24627"
  },
  {
    "session_id": 401003,
    "session_date": "1/15/2023 12:00:00 AM",
    "event_id": 771,
    "eventname": "2022 KING OF THE ICE 2022/2023",
    "speed_avg": 97.21259119999999,
    "speed_2sec": 99.802428,
    "speed_10sec": 98.91717200000001,
    "speed_100": 99.52277600000001,
    "speed_250": 99.039404,
    "speed_500": 97.53558000000001,
    "speed_mile": 76.470932,
    "speed_hour": 41.214408000000006,
    "speed_halfhour": 45.101756,
    "speed_24hour": 0.0,
    "speed_alpha_racing": 30.402432,
    "session_distance": 84.00077,
    "username": "Boris Ljubt\u0161enko",
    "flag": "EE",
    "sexe": "Men",
    "spotname": "Sarve",
    "sessionboard": "Custom Ice Sled-Al board Custom,  2022",
    "sessionsail": "Neilpryde RS3 5.8,  2003",
    "sessionfin": "Custom ice blade  0",
    "sessiongpstype": "Locosys GW-60",
    "sessionurl": "https://www.gps-icesailing.com/?mnu=user&val=401003&uid=26037"
  },
  {
    "session_id": 401047,
    "session_date": "1/10/2023 12:00:00 AM",
    "event_id": 771,
    "eventname": "2022 KING OF THE ICE 2022/2023",
    "speed_avg": 65.95453520000001,
    "speed_2sec": 70.020416,
    "speed_10sec": 68.21286400000001,
    "speed_100": 68.933292,
    "speed_250": 67.649856,
    "speed_500": 65.442272,
    "speed_mile": 49.461364,
    "speed_hour": 29.906096,
    "speed_halfhour": 38.10304800000001,
    "speed_24hour": 0.0,
    "speed_alpha_racing": 42.03114,
    "session_distance": 71.73136,
    "username": "Rob Myles",
    "flag": "US",
    "sexe": "Men",
    "spotname": "Lake Wentworth",
    "sessionboard": "Custom Carbon Freeskate,  1996",
    "sessionsail": "Sailworks Flyer 3.9,  2021",
    "sessionfin": "Custom ice blade  0",
    "sessiongpstype": "Locosys GW-60",
    "sessionurl": "https://www.gps-icesailing.com/?mnu=user&val=401047&uid=24421"
  },
  {
    "session_id": 401099,
    "session_date": "12/18/2022 12:00:00 AM",
    "event_id": 771,
    "eventname": "2022 KING OF THE ICE 2022/2023",
    "speed_avg": 43.6297864,
    "speed_2sec": 44.835068,
    "speed_10sec": 44.118344,
    "speed_100": 44.264652000000005,
    "speed_250": 43.253460000000004,
    "speed_500": 42.647856,
    "speed_mile": 41.664444,
    "speed_hour": 22.04806,
    "speed_halfhour": 25.822436,
    "speed_24hour": 0.0,
    "speed_alpha_racing": 22.833308000000002,
    "session_distance": 57.723392,
    "username": "Arjen Mol",
    "flag": "NL",
    "sexe": "Men",
    "spotname": "Veluwemeer - Nunspeet/Polsmaten",
    "sessionboard": "Custom Iceboard,  2008",
    "sessionsail": "Loftsails RACING BLADE 6.3,  2018",
    "sessionfin": "Custom ice blade  0",
    "sessiongpstype": "Locosys GW-60",
    "sessionurl": "https://www.gps-icesailing.com/?mnu=user&val=401099&uid=3716"
  },
  {
    "session_id": 401125,
    "session_date": "1/14/2023 12:00:00 AM",
    "event_id": 771,
    "eventname": "2022 KING OF THE ICE 2022/2023",
    "speed_avg": 56.57008079999999,
    "speed_2sec": 59.82145200000001,
    "speed_10sec": 59.39734400000001,
    "speed_100": 59.562172000000004,
    "speed_250": 59.260296000000004,
    "speed_500": 58.70099200000001,
    "speed_mile": 39.412411999999996,
    "speed_hour": 26.018748,
    "speed_halfhour": 30.756164000000002,
    "speed_24hour": 0.0,
    "speed_alpha_racing": 36.099184,
    "session_distance": 45.006783999999996,
    "username": "Koit Teder",
    "flag": "EE",
    "sexe": "Men",
    "spotname": "V\u00f5rtsj\u00e4rv",
    "sessionboard": "- Custom   Viljandi,  2021",
    "sessionsail": "GA-sails Phantom 6.4,  2020",
    "sessionfin": "Custom ice blade  0",
    "sessiongpstype": "Locosys GW-60",
    "sessionurl": "https://www.gps-icesailing.com/?mnu=user&val=401125&uid=25187"
  },
  {
    "session_id": 401128,
    "session_date": "1/5/2023 12:00:00 AM",
    "event_id": 771,
    "eventname": "2022 KING OF THE ICE 2022/2023",
    "speed_avg": 61.133779199999985,
    "speed_2sec": 64.33848,
    "speed_10sec": 63.223576,
    "speed_100": 63.769916,
    "speed_250": 62.717980000000004,
    "speed_500": 60.832644,
    "speed_mile": 55.13404,
    "speed_hour": 32.191464,
    "speed_halfhour": 36.778868,
    "speed_24hour": 0.0,
    "speed_alpha_racing": 38.601236,
    "session_distance": 130.247366,
    "username": "Koit Teder",
    "flag": "EE",
    "sexe": "Men",
    "spotname": "V\u00f5rtsj\u00e4rv",
    "sessionboard": "- Custom   Viljandi,  2021",
    "sessionsail": "GA-sails Phantom 6.4,  2020",
    "sessionfin": "Custom ice blade  0",
    "sessiongpstype": "Locosys GW-60",
    "sessionurl": "https://www.gps-icesailing.com/?mnu=user&val=401128&uid=25187"
  },
  {
    "session_id": 401129,
    "session_date": "12/31/2022 12:00:00 AM",
    "event_id": 771,
    "eventname": "2022 KING OF THE ICE 2022/2023",
    "speed_avg": 63.61175520000002,
    "speed_2sec": 65.08483600000001,
    "speed_10sec": 64.63850400000001,
    "speed_100": 64.90334,
    "speed_250": 64.23662,
    "speed_500": 63.179128,
    "speed_mile": 53.502428,
    "speed_hour": 31.828472,
    "speed_halfhour": 34.236072,
    "speed_24hour": 0.0,
    "speed_alpha_racing": 38.664204,
    "session_distance": 102.344088,
    "username": "Koit Teder",
    "flag": "EE",
    "sexe": "Men",
    "spotname": "V\u00f5rtsj\u00e4rv",
    "sessionboard": "- Custom   Viljandi,  2021",
    "sessionsail": "Gaastra Phantom  7.1,  2021",
    "sessionfin": "Custom ice blade  0",
    "sessiongpstype": "Locosys GW-60",
    "sessionurl": "https://www.gps-icesailing.com/?mnu=user&val=401129&uid=25187"
  },
  {
    "session_id": 401173,
    "session_date": "1/23/2023 12:00:00 AM",
    "event_id": 771,
    "eventname": "2022 KING OF THE ICE 2022/2023",
    "speed_avg": 42.256713600000005,
    "speed_2sec": 48.059400000000004,
    "speed_10sec": 46.261108,
    "speed_100": 46.881528,
    "speed_250": 43.807208,
    "speed_500": 38.04008,
    "speed_mile": 32.732248,
    "speed_hour": 0.0,
    "speed_halfhour": 0.0,
    "speed_24hour": 0.0,
    "speed_alpha_racing": 39.1698,
    "session_distance": 7.93809,
    "username": "Tommy Gustavsson",
    "flag": "SE",
    "sexe": "Men",
    "spotname": "Brunnbybaden",
    "sessionboard": "Hiberna 4 runner,  2009",
    "sessionsail": "Sailloft Hamburg Quad 3.3,  2013",
    "sessionfin": "Custom ice blade  0",
    "sessiongpstype": "Mobile Phone App",
    "sessionurl": "https://www.gps-icesailing.com/?mnu=user&val=401173&uid=24740"
  },
  {
    "session_id": 401183,
    "session_date": "1/23/2023 12:00:00 AM",
    "event_id": 771,
    "eventname": "2022 KING OF THE ICE 2022/2023",
    "speed_avg": 44.6672768,
    "speed_2sec": 49.139116,
    "speed_10sec": 47.427868000000004,
    "speed_100": 47.718632,
    "speed_250": 44.388736,
    "speed_500": 42.810832000000005,
    "speed_mile": 36.069552,
    "speed_hour": 0.0,
    "speed_halfhour": 23.940804,
    "speed_24hour": 0.0,
    "speed_alpha_racing": 38.20676,
    "session_distance": 11.97901,
    "username": "Tommy Gustavsson",
    "flag": "SE",
    "sexe": "Men",
    "spotname": "Brunnbybaden",
    "sessionboard": "Hiberna 4 runner,  2009",
    "sessionsail": "XO-Sails Shark 4.7,  2010",
    "sessionfin": "Custom ice blade  0",
    "sessiongpstype": "Mobile Phone App",
    "sessionurl": "https://www.gps-icesailing.com/?mnu=user&val=401183&uid=24740"
  },
  {
    "session_id": 401198,
    "session_date": "1/25/2023 12:00:00 AM",
    "event_id": 771,
    "eventname": "2022 KING OF THE ICE 2022/2023",
    "speed_avg": 59.4606824,
    "speed_2sec": 71.261256,
    "speed_10sec": 67.114628,
    "speed_100": 69.822252,
    "speed_250": 63.032819999999994,
    "speed_500": 52.46716,
    "speed_mile": 41.04217200000001,
    "speed_hour": 0.0,
    "speed_halfhour": 25.657608,
    "speed_24hour": 0.0,
    "speed_alpha_racing": 42.8275,
    "session_distance": 12.82919,
    "username": "Henrik M\u00e5rd",
    "flag": "SE",
    "sexe": "Men",
    "spotname": "Altasjon, Stockholm",
    "sessionboard": "Custom M\u00e5rdboard 4.1,  2016",
    "sessionsail": "Neilpryde RS Racing EVO 5 7.0,  2013",
    "sessionfin": "Custom ice blade  0",
    "sessiongpstype": "Locosys GW-60",
    "sessionurl": "https://www.gps-icesailing.com/?mnu=user&val=401198&uid=1468"
  },
  {
    "session_id": 401250,
    "session_date": "1/28/2023 12:00:00 AM",
    "event_id": 771,
    "eventname": "2022 KING OF THE ICE 2022/2023",
    "speed_avg": 41.3362696,
    "speed_2sec": 47.19636800000001,
    "speed_10sec": 45.620316,
    "speed_100": 46.048128000000005,
    "speed_250": 43.205308,
    "speed_500": 38.16972,
    "speed_mile": 31.32658,
    "speed_hour": 0.0,
    "speed_halfhour": 20.80722,
    "speed_24hour": 0.0,
    "speed_alpha_racing": 38.443816,
    "session_distance": 16.26956,
    "username": "Tommy Gustavsson",
    "flag": "SE",
    "sexe": "Men",
    "spotname": "Brunnbybaden",
    "sessionboard": "Hiberna 4 runner,  2009",
    "sessionsail": "Sailloft Hamburg Quad 3.3,  2013",
    "sessionfin": "Custom ice blade  0",
    "sessiongpstype": "Mobile Phone App",
    "sessionurl": "https://www.gps-icesailing.com/?mnu=user&val=401250&uid=24740"
  },
  {
    "session_id": 401258,
    "session_date": "1/28/2023 12:00:00 AM",
    "event_id": 771,
    "eventname": "2022 KING OF THE ICE 2022/2023",
    "speed_avg": 59.8988656,
    "speed_2sec": 63.471744,
    "speed_10sec": 61.812352,
    "speed_100": 62.766132,
    "speed_250": 60.212224000000006,
    "speed_500": 57.091604000000004,
    "speed_mile": 45.322144,
    "speed_hour": 0.0,
    "speed_halfhour": 0.0,
    "speed_24hour": 0.0,
    "speed_alpha_racing": 0.0,
    "session_distance": 8.671228,
    "username": "Koit Teder",
    "flag": "EE",
    "sexe": "Men",
    "spotname": "Saadj\u00e4rv",
    "sessionboard": "- Custom   Viljandi,  2021",
    "sessionsail": "GA-sails Phantom 6.4,  2020",
    "sessionfin": "Custom ice blade  0",
    "sessiongpstype": "Locosys GW-60",
    "sessionurl": "https://www.gps-icesailing.com/?mnu=user&val=401258&uid=25187"
  },
  {
    "session_id": 401290,
    "session_date": "1/8/2023 12:00:00 AM",
    "event_id": 771,
    "eventname": "2022 KING OF THE ICE 2022/2023",
    "speed_avg": 60.849682400000006,
    "speed_2sec": 75.754208,
    "speed_10sec": 74.444844,
    "speed_100": 75.137492,
    "speed_250": 73.689228,
    "speed_500": 68.183232,
    "speed_mile": 42.273752,
    "speed_hour": 21.846192,
    "speed_halfhour": 25.311284,
    "speed_24hour": 0.0,
    "speed_alpha_racing": 44.575788,
    "session_distance": 43.453269,
    "username": "Ramunas Glizickas",
    "flag": "LT",
    "sexe": "Men",
    "spotname": "Elektrenai",
    "sessionboard": "Custom G.R.I.B,  2022",
    "sessionsail": "GA-sails Vapor 5.2,  2018",
    "sessionfin": "Custom ice blade  0",
    "sessiongpstype": "fenix5",
    "sessionurl": "https://www.gps-icesailing.com/?mnu=user&val=401290&uid=26662"
  },
  {
    "session_id": 401293,
    "session_date": "1/29/2023 12:00:00 AM",
    "event_id": 771,
    "eventname": "2022 KING OF THE ICE 2022/2023",
    "speed_avg": 53.0364648,
    "speed_2sec": 54.882168,
    "speed_10sec": 53.83393600000001,
    "speed_100": 54.371016000000004,
    "speed_250": 52.89312,
    "speed_500": 51.78192000000001,
    "speed_mile": 41.59592000000001,
    "speed_hour": 26.142832000000002,
    "speed_halfhour": 30.39132,
    "speed_24hour": 0.0,
    "speed_alpha_racing": 39.379076000000005,
    "session_distance": 66.4517,
    "username": "Thomas Barr\u00e9",
    "flag": "SE",
    "sexe": "Men",
    "spotname": "Vallentunasj\u00f6n",
    "sessionboard": "not defined ,  0",
    "sessionsail": "Goya Mark 2 6.6,  2019",
    "sessionfin": "Custom ice blade  0",
    "sessiongpstype": "Garmin forerunner935",
    "sessionurl": "https://www.gps-icesailing.com/?mnu=user&val=401293&uid=24627"
  },
  {
    "session_id": 401345,
    "session_date": "1/28/2023 12:00:00 AM",
    "event_id": 771,
    "eventname": "2022 KING OF THE ICE 2022/2023",
    "speed_avg": 71.51275760000001,
    "speed_2sec": 81.49170400000001,
    "speed_10sec": 79.38598,
    "speed_100": 81.01574,
    "speed_250": 78.248852,
    "speed_500": 69.98337599999999,
    "speed_mile": 47.733448,
    "speed_hour": 29.187520000000003,
    "speed_halfhour": 31.982187999999997,
    "speed_24hour": 0.0,
    "speed_alpha_racing": 41.384792000000004,
    "session_distance": 60.964497,
    "username": "Mete Ciragan",
    "flag": "FI",
    "sexe": "Men",
    "spotname": "Espoonlahti Klobben",
    "sessionboard": "Custom ice,  2019",
    "sessionsail": "Loftsails Racing Blade 5.6,  2015",
    "sessionfin": "Custom ice blade  0",
    "sessiongpstype": "Garmin forerunner920xt",
    "sessionurl": "https://www.gps-icesailing.com/?mnu=user&val=401345&uid=5343"
  },
  {
    "session_id": 401348,
    "session_date": "1/30/2023 12:00:00 AM",
    "event_id": 771,
    "eventname": "2022 KING OF THE ICE 2022/2023",
    "speed_avg": 61.47084320000002,
    "speed_2sec": 67.75912400000001,
    "speed_10sec": 65.0052,
    "speed_100": 65.388564,
    "speed_250": 63.91437200000001,
    "speed_500": 61.721604,
    "speed_mile": 46.187028000000005,
    "speed_hour": 27.72444,
    "speed_halfhour": 29.824608,
    "speed_24hour": 0.0,
    "speed_alpha_racing": 30.446880000000004,
    "session_distance": 37.354366,
    "username": "Raido Ruse",
    "flag": "EE",
    "sexe": "Men",
    "spotname": "V\u00f5rtsj\u00e4rv",
    "sessionboard": "not defined ,  0",
    "sessionsail": "Cabrinha Wing 6.0,  2021",
    "sessionfin": "Custom ice blade  0",
    "sessiongpstype": "unknown",
    "sessionurl": "https://www.gps-icesailing.com/?mnu=user&val=401348&uid=26620"
  },
  {
    "session_id": 401352,
    "session_date": "1/30/2023 12:00:00 AM",
    "event_id": 771,
    "eventname": "2022 KING OF THE ICE 2022/2023",
    "speed_avg": 82.3354752,
    "speed_2sec": 86.406912,
    "speed_10sec": 84.25488800000001,
    "speed_100": 85.032728,
    "speed_250": 84.017832,
    "speed_500": 82.40474,
    "speed_mile": 52.122688,
    "speed_hour": 0.0,
    "speed_halfhour": 38.553084000000005,
    "speed_24hour": 0.0,
    "speed_alpha_racing": 44.335028,
    "session_distance": 28.337787,
    "username": "Giedrius Liutkus",
    "flag": "LT",
    "sexe": "Men",
    "spotname": "V\u00f5rtsj\u00e4rv",
    "sessionboard": "Hiberna ICE Skate,  2010",
    "sessionsail": "S2 Maui Venom 7.0,  2020",
    "sessionfin": "Custom ice blade  0",
    "sessiongpstype": "Garmin forerunner945LTE",
    "sessionurl": "https://www.gps-icesailing.com/?mnu=user&val=401352&uid=4506"
  },
  {
    "session_id": 401355,
    "session_date": "1/30/2023 12:00:00 AM",
    "event_id": 771,
    "eventname": "2022 KING OF THE ICE 2022/2023",
    "speed_avg": 76.6379824,
    "speed_2sec": 82.42881600000001,
    "speed_10sec": 77.11542800000001,
    "speed_100": 78.23774,
    "speed_250": 77.072832,
    "speed_500": 76.132016,
    "speed_mile": 60.206668,
    "speed_hour": 0.0,
    "speed_halfhour": 42.746012,
    "speed_24hour": 0.0,
    "speed_alpha_racing": 47.070432000000004,
    "session_distance": 28.789619,
    "username": "Giedrius Liutkus",
    "flag": "LT",
    "sexe": "Men",
    "spotname": "V\u00f5rtsj\u00e4rv",
    "sessionboard": "Hiberna ICE Skate,  2010",
    "sessionsail": "S2 Maui Venom 7.0,  2020",
    "sessionfin": "Custom ice blade  0",
    "sessiongpstype": "Garmin Forerunner 945 LTE",
    "sessionurl": "https://www.gps-icesailing.com/?mnu=user&val=401355&uid=4506"
  },
  {
    "session_id": 401381,
    "session_date": "1/30/2023 12:00:00 AM",
    "event_id": 771,
    "eventname": "2022 KING OF THE ICE 2022/2023",
    "speed_avg": 59.191031200000005,
    "speed_2sec": 66.19233200000001,
    "speed_10sec": 61.091924000000006,
    "speed_100": 62.592043999999994,
    "speed_250": 59.832564000000005,
    "speed_500": 57.926856,
    "speed_mile": 53.68022,
    "speed_hour": 28.565248,
    "speed_halfhour": 32.711876000000004,
    "speed_24hour": 0.0,
    "speed_alpha_racing": 29.230116,
    "session_distance": 51.293271,
    "username": "Raido Ruse",
    "flag": "EE",
    "sexe": "Men",
    "spotname": "Emaj\u00f5e j\u00f5esuu V\u00f5rtsj\u00e4rv",
    "sessionboard": "not defined ,  0",
    "sessionsail": "Cabrinha Wing 6.0,  2021",
    "sessionfin": "Custom ice blade  0",
    "sessiongpstype": "unknown",
    "sessionurl": "https://www.gps-icesailing.com/?mnu=user&val=401381&uid=26620"
  },
  {
    "session_id": 401416,
    "session_date": "1/30/2023 12:00:00 AM",
    "event_id": 771,
    "eventname": "2022 KING OF THE ICE 2022/2023",
    "speed_avg": 74.5252208,
    "speed_2sec": 80.11752,
    "speed_10sec": 79.58599600000001,
    "speed_100": 79.824904,
    "speed_250": 79.337828,
    "speed_500": 78.378492,
    "speed_mile": 62.94392400000001,
    "speed_hour": 41.053284000000005,
    "speed_halfhour": 46.814856,
    "speed_24hour": 0.0,
    "speed_alpha_racing": 47.30378400000001,
    "session_distance": 74.277788,
    "username": "Boris Ljubt\u0161enko",
    "flag": "EE",
    "sexe": "Men",
    "spotname": "V\u00f5rtsj\u00e4rv",
    "sessionboard": "Custom Ice Sled-Al board Custom,  2022",
    "sessionsail": "Neilpryde RS3 5.8,  2003",
    "sessionfin": "Custom ice blade  0",
    "sessiongpstype": "Locosys GW-60",
    "sessionurl": "https://www.gps-icesailing.com/?mnu=user&val=401416&uid=26037"
  },
  {
    "session_id": 401473,
    "session_date": "1/31/2023 12:00:00 AM",
    "event_id": 771,
    "eventname": "2022 KING OF THE ICE 2022/2023",
    "speed_avg": 59.6892192,
    "speed_2sec": 65.825636,
    "speed_10sec": 64.595908,
    "speed_100": 65.173732,
    "speed_250": 64.018084,
    "speed_500": 60.260375999999994,
    "speed_mile": 43.142340000000004,
    "speed_hour": 15.0012,
    "speed_halfhour": 20.301624,
    "speed_24hour": 0.0,
    "speed_alpha_racing": 33.802704,
    "session_distance": 52.652116,
    "username": "Koit Teder",
    "flag": "EE",
    "sexe": "Men",
    "spotname": "V\u00f5rtsj\u00e4rv",
    "sessionboard": "- Custom   Viljandi,  2021",
    "sessionsail": "GA-sails Phantom 6.4,  2020",
    "sessionfin": "Custom ice blade  0",
    "sessiongpstype": "Locosys GW-60",
    "sessionurl": "https://www.gps-icesailing.com/?mnu=user&val=401473&uid=25187"
  },
  {
    "session_id": 401630,
    "session_date": "1/30/2023 12:00:00 AM",
    "event_id": 771,
    "eventname": "2022 KING OF THE ICE 2022/2023",
    "speed_avg": 64.2377312,
    "speed_2sec": 68.327688,
    "speed_10sec": 67.12574,
    "speed_100": 67.67208000000001,
    "speed_250": 66.712744,
    "speed_500": 66.41086800000001,
    "speed_mile": 54.2173,
    "speed_hour": 18.003292000000002,
    "speed_halfhour": 25.896516000000002,
    "speed_24hour": 0.0,
    "speed_alpha_racing": 20.433116,
    "session_distance": 25.633964,
    "username": "Liisa Ljubt\u0161enko",
    "flag": "EE",
    "sexe": "Woman",
    "spotname": "V\u00f5rtsj\u00e4rv",
    "sessionboard": "- Ice Sled-Al board Custom,  2020",
    "sessionsail": "Neilpryde RS Racing 5.8,  2002",
    "sessionfin": "Custom ice blade  0",
    "sessiongpstype": "Locosys GW-60",
    "sessionurl": "https://www.gps-icesailing.com/?mnu=user&val=401630&uid=26042"
  },
  {
    "session_id": 401634,
    "session_date": "1/8/2023 12:00:00 AM",
    "event_id": 771,
    "eventname": "2022 KING OF THE ICE 2022/2023",
    "speed_avg": 79.2555992,
    "speed_2sec": 83.26406800000001,
    "speed_10sec": 82.28436,
    "speed_100": 82.915892,
    "speed_250": 82.204724,
    "speed_500": 81.030556,
    "speed_mile": 65.91823600000001,
    "speed_hour": 17.21434,
    "speed_halfhour": 29.907948000000005,
    "speed_24hour": 0.0,
    "speed_alpha_racing": 42.5497,
    "session_distance": 37.348756,
    "username": "Liisa Ljubt\u0161enko",
    "flag": "EE",
    "sexe": "Woman",
    "spotname": "Sarve",
    "sessionboard": "- Ice Sled-Al board Custom,  2020",
    "sessionsail": "Neilpryde RS Racing 5.8,  2002",
    "sessionfin": "Custom ice blade  0",
    "sessiongpstype": "Locosys GW-60",
    "sessionurl": "https://www.gps-icesailing.com/?mnu=user&val=401634&uid=26042"
  },
  {
    "session_id": 401673,
    "session_date": "2/4/2023 12:00:00 AM",
    "event_id": 771,
    "eventname": "2022 KING OF THE ICE 2022/2023",
    "speed_avg": 52.30048,
    "speed_2sec": 57.563864,
    "speed_10sec": 55.398876,
    "speed_100": 56.319320000000005,
    "speed_250": 53.407976000000005,
    "speed_500": 48.181632,
    "speed_mile": 41.092176,
    "speed_hour": 14.704880000000001,
    "speed_halfhour": 17.286568,
    "speed_24hour": 0.0,
    "speed_alpha_racing": 40.708812,
    "session_distance": 22.90134,
    "username": "Henrik M\u00e5rd",
    "flag": "SE",
    "sexe": "Men",
    "spotname": "Altasjon, Stockholm",
    "sessionboard": "Custom M\u00e5rdboard 4.1,  2016",
    "sessionsail": "Neilpryde RS Racing EVO 5 7.0,  2013",
    "sessionfin": "Custom ice blade  0",
    "sessiongpstype": "Locosys GW-60",
    "sessionurl": "https://www.gps-icesailing.com/?mnu=user&val=401673&uid=1468"
  },
  {
    "session_id": 401712,
    "session_date": "2/5/2023 12:00:00 AM",
    "event_id": 771,
    "eventname": "2022 KING OF THE ICE 2022/2023",
    "speed_avg": 37.71783200000001,
    "speed_2sec": 40.697700000000005,
    "speed_10sec": 38.743840000000006,
    "speed_100": 38.77162,
    "speed_250": 35.423204,
    "speed_500": 34.532392,
    "speed_mile": 29.439392,
    "speed_hour": 0.0,
    "speed_halfhour": 0.0,
    "speed_24hour": 0.0,
    "speed_alpha_racing": 34.949092,
    "session_distance": 6.57273,
    "username": "Tommy Gustavsson",
    "flag": "SE",
    "sexe": "Men",
    "spotname": "Skarholmen, Ekoln",
    "sessionboard": "Hiberna 4 runner,  2009",
    "sessionsail": "XO-Sails Shark 4.7,  2010",
    "sessionfin": "Custom ice blade  0",
    "sessiongpstype": "Mobile Phone App",
    "sessionurl": "https://www.gps-icesailing.com/?mnu=user&val=401712&uid=24740"
  },
  {
    "session_id": 401729,
    "session_date": "2/5/2023 12:00:00 AM",
    "event_id": 771,
    "eventname": "2022 KING OF THE ICE 2022/2023",
    "speed_avg": 54.228041600000005,
    "speed_2sec": 57.545344,
    "speed_10sec": 56.55822800000001,
    "speed_100": 56.863808000000006,
    "speed_250": 55.493328,
    "speed_500": 50.57812,
    "speed_mile": 41.597772,
    "speed_hour": 15.21418,
    "speed_halfhour": 22.977764,
    "speed_24hour": 0.0,
    "speed_alpha_racing": 41.518136,
    "session_distance": 20.476290000000002,
    "username": "Henrik M\u00e5rd",
    "flag": "SE",
    "sexe": "Men",
    "spotname": "Drevviken",
    "sessionboard": "Custom M\u00e5rdboard 4.1,  2016",
    "sessionsail": "Neilpryde RS Racing EVO 5 7.0,  2013",
    "sessionfin": "Custom ice blade  0",
    "sessiongpstype": "Locosys GW-60",
    "sessionurl": "https://www.gps-icesailing.com/?mnu=user&val=401729&uid=1468"
  },
  {
    "session_id": 401733,
    "session_date": "2/3/2023 12:00:00 AM",
    "event_id": 771,
    "eventname": "2022 KING OF THE ICE 2022/2023",
    "speed_avg": 91.34952960000001,
    "speed_2sec": 97.344824,
    "speed_10sec": 95.311328,
    "speed_100": 97.065172,
    "speed_250": 95.277992,
    "speed_500": 92.398132,
    "speed_mile": 51.68932,
    "speed_hour": 23.505584000000002,
    "speed_halfhour": 28.105952000000002,
    "speed_24hour": 0.0,
    "speed_alpha_racing": 49.889176,
    "session_distance": 54.811629999999994,
    "username": "Jeffrey Brown",
    "flag": "US",
    "sexe": "Men",
    "spotname": "Lake Winnipesaukee",
    "sessionboard": "Custom Ice-O-Later,  2000",
    "sessionsail": "Custom JBD Ice Speed 3.4,  2020",
    "sessionfin": "Custom ice blade  0",
    "sessiongpstype": "Locosys GT-31",
    "sessionurl": "https://www.gps-icesailing.com/?mnu=user&val=401733&uid=24310"
  },
  {
    "session_id": 401736,
    "session_date": "2/4/2023 12:00:00 AM",
    "event_id": 771,
    "eventname": "2022 KING OF THE ICE 2022/2023",
    "speed_avg": 70.9782704,
    "speed_2sec": 74.250384,
    "speed_10sec": 72.06502400000001,
    "speed_100": 73.511436,
    "speed_250": 70.864928,
    "speed_500": 69.722244,
    "speed_mile": 20.373852,
    "speed_hour": 35.360236,
    "speed_halfhour": 46.78152000000001,
    "speed_24hour": 0.0,
    "speed_alpha_racing": 51.854148,
    "session_distance": 40.86576,
    "username": "Jeffrey Brown",
    "flag": "US",
    "sexe": "Men",
    "spotname": "Lake Winnipesaukee",
    "sessionboard": "Custom Ice-O-Later,  2000",
    "sessionsail": "Custom JBD Ice Speed 3.7,  2020",
    "sessionfin": "Custom ice blade  0",
    "sessiongpstype": "Locosys GT-31",
    "sessionurl": "https://www.gps-icesailing.com/?mnu=user&val=401736&uid=24310"
  },
  {
    "session_id": 401828,
    "session_date": "2/4/2023 12:00:00 AM",
    "event_id": 771,
    "eventname": "2022 KING OF THE ICE 2022/2023",
    "speed_avg": 76.41352,
    "speed_2sec": 85.140144,
    "speed_10sec": 84.37712,
    "speed_100": 84.838268,
    "speed_250": 84.223404,
    "speed_500": 81.44170000000001,
    "speed_mile": 57.121236,
    "speed_hour": 47.344528000000004,
    "speed_halfhour": 48.009396,
    "speed_24hour": 0.0,
    "speed_alpha_racing": 46.798187999999996,
    "session_distance": 93.97964,
    "username": "Rob Myles",
    "flag": "US",
    "sexe": "Men",
    "spotname": "Lake Winnipesaukee",
    "sessionboard": "Custom Carbon Freeskate,  1996",
    "sessionsail": "Custom JBD Ice Speed 3.4,  2000",
    "sessionfin": "Custom ice blade  0",
    "sessiongpstype": "Locosys GW-60",
    "sessionurl": "https://www.gps-icesailing.com/?mnu=user&val=401828&uid=24421"
  },
  {
    "session_id": 401829,
    "session_date": "2/3/2023 12:00:00 AM",
    "event_id": 771,
    "eventname": "2022 KING OF THE ICE 2022/2023",
    "speed_avg": 86.6710072,
    "speed_2sec": 93.042628,
    "speed_10sec": 91.96106,
    "speed_100": 92.835204,
    "speed_250": 92.024028,
    "speed_500": 87.707016,
    "speed_mile": 50.9763,
    "speed_hour": 20.959084,
    "speed_halfhour": 26.148388,
    "speed_24hour": 0.0,
    "speed_alpha_racing": 41.40331200000001,
    "session_distance": 60.40343,
    "username": "Rob Myles",
    "flag": "US",
    "sexe": "Men",
    "spotname": "Lake Winnipesaukee",
    "sessionboard": "Custom Carbon Freeskate,  1996",
    "sessionsail": "Custom JBD Ice Speed 3.4,  2000",
    "sessionfin": "Custom ice blade  0",
    "sessiongpstype": "Locosys GW-60",
    "sessionurl": "https://www.gps-icesailing.com/?mnu=user&val=401829&uid=24421"
  },
  {
    "session_id": 401842,
    "session_date": "2/4/2023 12:00:00 AM",
    "event_id": 771,
    "eventname": "2022 KING OF THE ICE 2022/2023",
    "speed_avg": 61.51973600000001,
    "speed_2sec": 72.437276,
    "speed_10sec": 71.04272,
    "speed_100": 72.196516,
    "speed_250": 69.864848,
    "speed_500": 60.047396000000006,
    "speed_mile": 41.286636,
    "speed_hour": 0.0,
    "speed_halfhour": 24.39084,
    "speed_24hour": 0.0,
    "speed_alpha_racing": 41.388496,
    "session_distance": 26.330288,
    "username": "Mete Ciragan",
    "flag": "FI",
    "sexe": "Men",
    "spotname": "Espoonlahti Klobben",
    "sessionboard": "Custom ice,  2019",
    "sessionsail": "Loftsails Racing Blade 5.6,  2015",
    "sessionfin": "Custom ice blade  0",
    "sessiongpstype": "Garmin forerunner920xt",
    "sessionurl": "https://www.gps-icesailing.com/?mnu=user&val=401842&uid=5343"
  },
  {
    "session_id": 401850,
    "session_date": "1/31/2023 12:00:00 AM",
    "event_id": 771,
    "eventname": "2022 KING OF THE ICE 2022/2023",
    "speed_avg": 64.4896032,
    "speed_2sec": 76.84873999999999,
    "speed_10sec": 75.322692,
    "speed_100": 75.81162,
    "speed_250": 74.650416,
    "speed_500": 70.714916,
    "speed_mile": 55.354428,
    "speed_hour": 19.051524000000004,
    "speed_halfhour": 29.048620000000003,
    "speed_24hour": 0.0,
    "speed_alpha_racing": 34.8639,
    "session_distance": 40.850935,
    "username": "Giedrius Liutkus",
    "flag": "LT",
    "sexe": "Men",
    "spotname": "V\u00f5rtsj\u00e4rv",
    "sessionboard": "Hiberna ICE Skate,  2010",
    "sessionsail": "S2 Maui Venom 7.0,  2020",
    "sessionfin": "Custom ice blade  0",
    "sessiongpstype": "unknown",
    "sessionurl": "https://www.gps-icesailing.com/?mnu=user&val=401850&uid=4506"
  },
  {
    "session_id": 401851,
    "session_date": "2/4/2023 12:00:00 AM",
    "event_id": 771,
    "eventname": "2022 KING OF THE ICE 2022/2023",
    "speed_avg": 57.5594192,
    "speed_2sec": 61.40306,
    "speed_10sec": 58.20836,
    "speed_100": 58.667656,
    "speed_250": 57.797216,
    "speed_500": 57.004560000000005,
    "speed_mile": 53.622808000000006,
    "speed_hour": 47.85197600000001,
    "speed_halfhour": 48.246452,
    "speed_24hour": 0.0,
    "speed_alpha_racing": 20.383112,
    "session_distance": 63.047971,
    "username": "Giedrius Liutkus",
    "flag": "LT",
    "sexe": "Men",
    "spotname": "V\u00f5rtsj\u00e4rv",
    "sessionboard": "Hiberna ICE Skate,  2010",
    "sessionsail": "S2 Maui Venom 7.0,  2020",
    "sessionfin": "Custom ice blade  0",
    "sessiongpstype": "unknown",
    "sessionurl": "https://www.gps-icesailing.com/?mnu=user&val=401851&uid=4506"
  },
  {
    "session_id": 401865,
    "session_date": "2/7/2023 12:00:00 AM",
    "event_id": 771,
    "eventname": "2022 KING OF THE ICE 2022/2023",
    "speed_avg": 37.24483120000001,
    "speed_2sec": 39.438340000000004,
    "speed_10sec": 38.473448000000005,
    "speed_100": 38.51234,
    "speed_250": 37.315948000000006,
    "speed_500": 35.110216,
    "speed_mile": 32.545196000000004,
    "speed_hour": 0.0,
    "speed_halfhour": 0.0,
    "speed_24hour": 0.0,
    "speed_alpha_racing": 34.293484,
    "session_distance": 5.8998800000000005,
    "username": "Tommy Gustavsson",
    "flag": "SE",
    "sexe": "Men",
    "spotname": "Skarholmen, Ekoln",
    "sessionboard": "Hiberna 4 runner,  2009",
    "sessionsail": "XO-Sails Shark 4.7,  2010",
    "sessionfin": "Custom ice blade  0",
    "sessiongpstype": "Mobile Phone App",
    "sessionurl": "https://www.gps-icesailing.com/?mnu=user&val=401865&uid=24740"
  },
  {
    "session_id": 401866,
    "session_date": "2/3/2023 12:00:00 AM",
    "event_id": 771,
    "eventname": "2022 KING OF THE ICE 2022/2023",
    "speed_avg": 64.71480640000001,
    "speed_2sec": 75.45603600000001,
    "speed_10sec": 72.735448,
    "speed_100": 74.87265599999999,
    "speed_250": 71.32792800000001,
    "speed_500": 67.127592,
    "speed_mile": 32.911892,
    "speed_hour": 7.706172,
    "speed_halfhour": 9.728556000000001,
    "speed_24hour": 0.0,
    "speed_alpha_racing": 29.402352,
    "session_distance": 18.1203,
    "username": "Chad Lyons",
    "flag": "US",
    "sexe": "Men",
    "spotname": "Lake Winnipesaukee",
    "sessionboard": "Custom Ice-O-Tope ,  1995",
    "sessionsail": "Custom JBD Ice Speed 3.4,  2000",
    "sessionfin": "Custom ice blade  0",
    "sessiongpstype": "Locosys GT-31",
    "sessionurl": "https://www.gps-icesailing.com/?mnu=user&val=401866&uid=24377"
  },
  {
    "session_id": 401900,
    "session_date": "2/9/2023 12:00:00 AM",
    "event_id": 771,
    "eventname": "2022 KING OF THE ICE 2022/2023",
    "speed_avg": 36.2443808,
    "speed_2sec": 72.928056,
    "speed_10sec": 46.940792,
    "speed_100": 48.276084000000004,
    "speed_250": 0.0,
    "speed_500": 0.0,
    "speed_mile": 0.0,
    "speed_hour": 0.0,
    "speed_halfhour": 0.0,
    "speed_24hour": 0.0,
    "speed_alpha_racing": 0.0,
    "session_distance": 16.21638,
    "username": "Feodor Gurvits",
    "flag": "FI",
    "sexe": "Men",
    "spotname": "Espoonlahti Klobben",
    "sessionboard": "Custom ALBoard,  2018",
    "sessionsail": "Custom MW Sails Nexus 5.9,  2019",
    "sessionfin": "Custom ice blade  0",
    "sessiongpstype": "Suunto Ambit Series",
    "sessionurl": "https://www.gps-icesailing.com/?mnu=user&val=401900&uid=24385"
  },
  {
    "session_id": 401906,
    "session_date": "2/9/2023 12:00:00 AM",
    "event_id": 771,
    "eventname": "2022 KING OF THE ICE 2022/2023",
    "speed_avg": 75.6334576,
    "speed_2sec": 80.593484,
    "speed_10sec": 78.587768,
    "speed_100": 80.08048000000001,
    "speed_250": 78.40442,
    "speed_500": 76.17831600000001,
    "speed_mile": 44.3091,
    "speed_hour": 25.615012,
    "speed_halfhour": 25.75206,
    "speed_24hour": 0.0,
    "speed_alpha_racing": 33.1508,
    "session_distance": 40.035088,
    "username": "Valde Viiding",
    "flag": "EE",
    "sexe": "Men",
    "spotname": "Harku j\u00e4rv",
    "sessionboard": "not defined ,  0",
    "sessionsail": "Point-7 AC-ONE 5.0,  2018",
    "sessionfin": "Custom ice blade  0",
    "sessiongpstype": "Locosys GW-60",
    "sessionurl": "https://www.gps-icesailing.com/?mnu=user&val=401906&uid=21996"
  },
  {
    "session_id": 401920,
    "session_date": "2/9/2023 12:00:00 AM",
    "event_id": 771,
    "eventname": "2022 KING OF THE ICE 2022/2023",
    "speed_avg": 75.78384000000001,
    "speed_2sec": 81.147232,
    "speed_10sec": 78.587768,
    "speed_100": 80.767572,
    "speed_250": 77.22284400000001,
    "speed_500": 66.73682,
    "speed_mile": 41.553324,
    "speed_hour": 23.261120000000002,
    "speed_halfhour": 26.370628000000004,
    "speed_24hour": 0.0,
    "speed_alpha_racing": 39.710584000000004,
    "session_distance": 33.835887,
    "username": "Mete Ciragan",
    "flag": "FI",
    "sexe": "Men",
    "spotname": "Espoonlahti Klobben",
    "sessionboard": "Custom ice,  2019",
    "sessionsail": "Loftsails Racing Blade 5.6,  2015",
    "sessionfin": "Custom ice blade  0",
    "sessiongpstype": "Garmin forerunner920xt",
    "sessionurl": "https://www.gps-icesailing.com/?mnu=user&val=401920&uid=5343"
  },
  {
    "session_id": 401950,
    "session_date": "2/10/2023 12:00:00 AM",
    "event_id": 771,
    "eventname": "2022 KING OF THE ICE 2022/2023",
    "speed_avg": 69.20627680000001,
    "speed_2sec": 74.772648,
    "speed_10sec": 71.76870400000001,
    "speed_100": 73.69108,
    "speed_250": 70.44082,
    "speed_500": 62.460552,
    "speed_mile": 48.796496,
    "speed_hour": 24.953848,
    "speed_halfhour": 30.961736000000002,
    "speed_24hour": 0.0,
    "speed_alpha_racing": 50.72628,
    "session_distance": 58.43946,
    "username": "Henrik M\u00e5rd",
    "flag": "SE",
    "sexe": "Men",
    "spotname": "Altasjon, Stockholm",
    "sessionboard": "Custom M\u00e5rdboard 4.1,  2016",
    "sessionsail": "Gaastra Vapor 5.5,  2007",
    "sessionfin": "Custom ice blade  0",
    "sessiongpstype": "Locosys GW-60",
    "sessionurl": "https://www.gps-icesailing.com/?mnu=user&val=401950&uid=1468"
  },
  {
    "session_id": 401954,
    "session_date": "2/10/2023 12:00:00 AM",
    "event_id": 771,
    "eventname": "2022 KING OF THE ICE 2022/2023",
    "speed_avg": 91.05802480000001,
    "speed_2sec": 94.4983,
    "speed_10sec": 92.65741200000001,
    "speed_100": 94.105676,
    "speed_250": 92.722232,
    "speed_500": 89.42011600000001,
    "speed_mile": 72.489132,
    "speed_hour": 40.432864,
    "speed_halfhour": 45.61476,
    "speed_24hour": 0.0,
    "speed_alpha_racing": 47.042652000000004,
    "session_distance": 98.380757,
    "username": "Jakub Salek",
    "flag": "PL",
    "sexe": "Men",
    "spotname": "Haapsalu Eeslaht",
    "sessionboard": "Custom  Slalom Mroz 4,  2017",
    "sessionsail": "Loft Sails Racing blade 5.0,  2022",
    "sessionfin": "Custom ice blade  0",
    "sessiongpstype": "Motion",
    "sessionurl": "https://www.gps-icesailing.com/?mnu=user&val=401954&uid=25179"
  },
  {
    "session_id": 401957,
    "session_date": "2/10/2023 12:00:00 AM",
    "event_id": 771,
    "eventname": "2022 KING OF THE ICE 2022/2023",
    "speed_avg": 69.17553360000001,
    "speed_2sec": 73.674412,
    "speed_10sec": 70.5612,
    "speed_100": 71.37608,
    "speed_250": 69.659276,
    "speed_500": 63.25506000000001,
    "speed_mile": 48.69834000000001,
    "speed_hour": 38.723468,
    "speed_halfhour": 45.064716,
    "speed_24hour": 0.0,
    "speed_alpha_racing": 48.7539,
    "session_distance": 109.43289,
    "username": "Tobias Bodin",
    "flag": "SE",
    "sexe": "Men",
    "spotname": "Altasjon, Stockholm",
    "sessionboard": "Custom Sharp4,  2012",
    "sessionsail": "Loftsails PureLip 4.7,  2021",
    "sessionfin": "Custom ice blade  0",
    "sessiongpstype": "Locosys GT-31",
    "sessionurl": "https://www.gps-icesailing.com/?mnu=user&val=401957&uid=5893"
  },
  {
    "session_id": 401968,
    "session_date": "2/10/2023 12:00:00 AM",
    "event_id": 771,
    "eventname": "2022 KING OF THE ICE 2022/2023",
    "speed_avg": 74.7159768,
    "speed_2sec": 82.295472,
    "speed_10sec": 80.087888,
    "speed_100": 82.041748,
    "speed_250": 79.554512,
    "speed_500": 71.872416,
    "speed_mile": 41.056988000000004,
    "speed_hour": 16.766156000000002,
    "speed_halfhour": 21.533204,
    "speed_24hour": 0.0,
    "speed_alpha_racing": 33.135984,
    "session_distance": 41.289286,
    "username": "Valde Viiding",
    "flag": "EE",
    "sexe": "Men",
    "spotname": "Harku j\u00e4rv",
    "sessionboard": "not defined ,  0",
    "sessionsail": "Point-7 AC-ONE 5.0,  2018",
    "sessionfin": "Custom ice blade  0",
    "sessiongpstype": "Locosys GW-60",
    "sessionurl": "https://www.gps-icesailing.com/?mnu=user&val=401968&uid=21996"
  },
  {
    "session_id": 402010,
    "session_date": "2/11/2023 12:00:00 AM",
    "event_id": 771,
    "eventname": "2022 KING OF THE ICE 2022/2023",
    "speed_avg": 62.26349920000001,
    "speed_2sec": 68.409176,
    "speed_10sec": 64.84592800000001,
    "speed_100": 65.84786,
    "speed_250": 62.795764,
    "speed_500": 61.06044,
    "speed_mile": 52.726440000000004,
    "speed_hour": 24.068592000000002,
    "speed_halfhour": 33.154504,
    "speed_24hour": 0.0,
    "speed_alpha_racing": 19.981228,
    "session_distance": 38.583508,
    "username": "Giedrius Liutkus",
    "flag": "LT",
    "sexe": "Men",
    "spotname": "Kauno Marios",
    "sessionboard": "Hiberna ICE Skate,  2010",
    "sessionsail": "S2 Maui Venom 7.0,  2020",
    "sessionfin": "Custom ice blade  0",
    "sessiongpstype": "Garmin",
    "sessionurl": "https://www.gps-icesailing.com/?mnu=user&val=402010&uid=4506"
  },
  {
    "session_id": 402049,
    "session_date": "2/10/2023 12:00:00 AM",
    "event_id": 771,
    "eventname": "2022 KING OF THE ICE 2022/2023",
    "speed_avg": 27.9703856,
    "speed_2sec": 31.100636,
    "speed_10sec": 29.098624,
    "speed_100": 27.922604,
    "speed_250": 24.050072000000004,
    "speed_500": 22.53884,
    "speed_mile": 15.967944000000001,
    "speed_hour": 7.919152,
    "speed_halfhour": 9.424828000000002,
    "speed_24hour": 0.0,
    "speed_alpha_racing": 24.127856,
    "session_distance": 17.003758,
    "username": "Andras Farkas",
    "flag": "HU",
    "sexe": "Men",
    "spotname": "Cs\u00e1kv\u00e1r",
    "sessionboard": "not defined ,  0",
    "sessionsail": "Loft Sails Switchblade 6.8,  2021",
    "sessionfin": "Custom ice blade  0",
    "sessiongpstype": "unknown",
    "sessionurl": "https://www.gps-icesailing.com/?mnu=user&val=402049&uid=25268"
  },
  {
    "session_id": 402080,
    "session_date": "2/10/2023 12:00:00 AM",
    "event_id": 771,
    "eventname": "2022 KING OF THE ICE 2022/2023",
    "speed_avg": 90.87319520000001,
    "speed_2sec": 95.144648,
    "speed_10sec": 93.73342400000001,
    "speed_100": 94.509412,
    "speed_250": 93.764908,
    "speed_500": 91.11284400000001,
    "speed_mile": 50.77258,
    "speed_hour": 32.939672,
    "speed_halfhour": 34.639808,
    "speed_24hour": 0.0,
    "speed_alpha_racing": 39.414264,
    "session_distance": 36.795964,
    "username": "Boris Ljubt\u0161enko",
    "flag": "EE",
    "sexe": "Men",
    "spotname": "Sarve",
    "sessionboard": "Custom Ice Sled-Al board Custom,  2022",
    "sessionsail": "Neilpryde RS3 5.8,  2003",
    "sessionfin": "Custom ice blade  0",
    "sessiongpstype": "Locosys GW-60",
    "sessionurl": "https://www.gps-icesailing.com/?mnu=user&val=402080&uid=26037"
  },
  {
    "session_id": 402081,
    "session_date": "2/10/2023 12:00:00 AM",
    "event_id": 771,
    "eventname": "2022 KING OF THE ICE 2022/2023",
    "speed_avg": 67.06462400000001,
    "speed_2sec": 73.76701200000001,
    "speed_10sec": 71.092724,
    "speed_100": 73.14103600000001,
    "speed_250": 69.64816400000001,
    "speed_500": 65.04223999999999,
    "speed_mile": 38.87718400000001,
    "speed_hour": 22.796268,
    "speed_halfhour": 25.220536000000003,
    "speed_24hour": 0.0,
    "speed_alpha_racing": 31.037668000000004,
    "session_distance": 28.545582999999997,
    "username": "Raido Ruse",
    "flag": "EE",
    "sexe": "Men",
    "spotname": "Kahala j\u00e4rv",
    "sessionboard": "not defined ,  0",
    "sessionsail": "Cabrinha Wing 6.0,  2021",
    "sessionfin": "Custom ice blade  0",
    "sessiongpstype": "unknown",
    "sessionurl": "https://www.gps-icesailing.com/?mnu=user&val=402081&uid=26620"
  },
  {
    "session_id": 402095,
    "session_date": "1/30/2023 12:00:00 AM",
    "event_id": 771,
    "eventname": "2022 KING OF THE ICE 2022/2023",
    "speed_avg": 71.07198160000002,
    "speed_2sec": 74.974516,
    "speed_10sec": 74.326316,
    "speed_100": 74.83932,
    "speed_250": 74.109632,
    "speed_500": 72.753968,
    "speed_mile": 66.74793199999999,
    "speed_hour": 22.136956,
    "speed_halfhour": 23.914876000000003,
    "speed_24hour": 0.0,
    "speed_alpha_racing": 0.0,
    "session_distance": 31.500732,
    "username": "Koit Teder",
    "flag": "EE",
    "sexe": "Men",
    "spotname": "V\u00f5rtsj\u00e4rv",
    "sessionboard": "not defined ,  0",
    "sessionsail": "GA-sails Phantom 6.4,  2020",
    "sessionfin": "Custom ice blade  0",
    "sessiongpstype": "Locosys GW-60",
    "sessionurl": "https://www.gps-icesailing.com/?mnu=user&val=402095&uid=25187"
  },
  {
    "session_id": 402272,
    "session_date": "2/18/2023 12:00:00 AM",
    "event_id": 771,
    "eventname": "2022 KING OF THE ICE 2022/2023",
    "speed_avg": 83.32036880000001,
    "speed_2sec": 90.23314400000001,
    "speed_10sec": 89.07564400000001,
    "speed_100": 90.06276000000001,
    "speed_250": 88.903408,
    "speed_500": 84.577136,
    "speed_mile": 71.281628,
    "speed_hour": 37.46596,
    "speed_halfhour": 44.818400000000004,
    "speed_24hour": 0.0,
    "speed_alpha_racing": 53.272780000000004,
    "session_distance": 88.53605999999999,
    "username": "Henrik M\u00e5rd",
    "flag": "SE",
    "sexe": "Men",
    "spotname": "Fysingen",
    "sessionboard": "Custom M\u00e5rdboard 4.1,  2016",
    "sessionsail": "Neilpryde Evo 2 5.5m2 recut to 4.75m2 4.8,  2016",
    "sessionfin": "Custom ice blade  0",
    "sessiongpstype": "Locosys GW-60",
    "sessionurl": "https://www.gps-icesailing.com/?mnu=user&val=402272&uid=1468"
  },
  {
    "session_id": 402312,
    "session_date": "2/18/2023 12:00:00 AM",
    "event_id": 771,
    "eventname": "2022 KING OF THE ICE 2022/2023",
    "speed_avg": 67.62689119999999,
    "speed_2sec": 75.207868,
    "speed_10sec": 73.665152,
    "speed_100": 74.93192,
    "speed_250": 72.883608,
    "speed_500": 68.392508,
    "speed_mile": 47.483428,
    "speed_hour": 23.533364000000002,
    "speed_halfhour": 25.792804,
    "speed_24hour": 0.0,
    "speed_alpha_racing": 41.562584,
    "session_distance": 67.306108,
    "username": "Thomas Barr\u00e9",
    "flag": "SE",
    "sexe": "Men",
    "spotname": "Vallentunasj\u00f6n",
    "sessionboard": "not defined ,  0",
    "sessionsail": "Simmer Sails Crossover 4.2,  2004",
    "sessionfin": "Custom ice blade  0",
    "sessiongpstype": "Garmin forerunner935",
    "sessionurl": "https://www.gps-icesailing.com/?mnu=user&val=402312&uid=24627"
  },
  {
    "session_id": 402326,
    "session_date": "2/18/2023 12:00:00 AM",
    "event_id": 771,
    "eventname": "2022 KING OF THE ICE 2022/2023",
    "speed_avg": 78.91631280000001,
    "speed_2sec": 84.59936,
    "speed_10sec": 83.51223600000002,
    "speed_100": 84.31230000000001,
    "speed_250": 83.352964,
    "speed_500": 77.378412,
    "speed_mile": 71.420528,
    "speed_hour": 49.611376,
    "speed_halfhour": 50.533672,
    "speed_24hour": 0.0,
    "speed_alpha_racing": 53.965428,
    "session_distance": 118.32409,
    "username": "Tobias Bodin",
    "flag": "SE",
    "sexe": "Men",
    "spotname": "Fysingen",
    "sessionboard": "Custom Sharp4,  2012",
    "sessionsail": "Maui Sails TR3 4.7,  2007",
    "sessionfin": "Custom ice blade  0",
    "sessiongpstype": "Locosys GT-31",
    "sessionurl": "https://www.gps-icesailing.com/?mnu=user&val=402326&uid=5893"
  },
  {
    "session_id": 402393,
    "session_date": "2/18/2023 12:00:00 AM",
    "event_id": 771,
    "eventname": "2022 KING OF THE ICE 2022/2023",
    "speed_avg": 46.06035120000001,
    "speed_2sec": 49.111336,
    "speed_10sec": 48.67982,
    "speed_100": 48.748344,
    "speed_250": 48.366832,
    "speed_500": 47.853828,
    "speed_mile": 45.131388,
    "speed_hour": 23.45558,
    "speed_halfhour": 29.824608,
    "speed_24hour": 0.0,
    "speed_alpha_racing": 38.13268,
    "session_distance": 66.147706,
    "username": "Koit Teder",
    "flag": "EE",
    "sexe": "Men",
    "spotname": "V\u00f5rtsj\u00e4rv",
    "sessionboard": "not defined ,  0",
    "sessionsail": "GA-sails Phantom 6.4,  2020",
    "sessionfin": "Custom ice blade  0",
    "sessiongpstype": "Locosys GW-60",
    "sessionurl": "https://www.gps-icesailing.com/?mnu=user&val=402393&uid=25187"
  },
  {
    "session_id": 402407,
    "session_date": "2/18/2023 12:00:00 AM",
    "event_id": 771,
    "eventname": "2022 KING OF THE ICE 2022/2023",
    "speed_avg": 78.40442,
    "speed_2sec": 83.056644,
    "speed_10sec": 82.44178000000001,
    "speed_100": 82.804772,
    "speed_250": 82.38436800000001,
    "speed_500": 80.106408,
    "speed_mile": 57.045304,
    "speed_hour": 39.856892,
    "speed_halfhour": 44.870256000000005,
    "speed_24hour": 0.0,
    "speed_alpha_racing": 52.465308,
    "session_distance": 47.594043,
    "username": "Stefan S\u00f6derlund",
    "flag": "SE",
    "sexe": "Men",
    "spotname": "Framn\u00e4s",
    "sessionboard": "not defined ,  0",
    "sessionsail": "Maui Sails TR-6 5.5,  2010",
    "sessionfin": "Custom ice blade  0",
    "sessiongpstype": "unknown",
    "sessionurl": "https://www.gps-icesailing.com/?mnu=user&val=402407&uid=25296"
  },
  {
    "session_id": 402428,
    "session_date": "2/19/2023 12:00:00 AM",
    "event_id": 771,
    "eventname": "2022 KING OF THE ICE 2022/2023",
    "speed_avg": 71.8842688,
    "speed_2sec": 75.222684,
    "speed_10sec": 73.076216,
    "speed_100": 74.613376,
    "speed_250": 71.809448,
    "speed_500": 69.512968,
    "speed_mile": 52.782000000000004,
    "speed_hour": 21.044276,
    "speed_halfhour": 36.369576,
    "speed_24hour": 0.0,
    "speed_alpha_racing": 44.572084000000004,
    "session_distance": 63.103001,
    "username": "Thomas Barr\u00e9",
    "flag": "SE",
    "sexe": "Men",
    "spotname": "Ullnasj\u00f6n",
    "sessionboard": "not defined ,  0",
    "sessionsail": "Simmer Sails Crossover 4.2,  2004",
    "sessionfin": "Custom ice blade  0",
    "sessiongpstype": "Garmin forerunner935",
    "sessionurl": "https://www.gps-icesailing.com/?mnu=user&val=402428&uid=24627"
  },
  {
    "session_id": 402432,
    "session_date": "2/19/2023 12:00:00 AM",
    "event_id": 771,
    "eventname": "2022 KING OF THE ICE 2022/2023",
    "speed_avg": 50.3766224,
    "speed_2sec": 54.737712,
    "speed_10sec": 53.31167200000001,
    "speed_100": 53.815416,
    "speed_250": 50.9763,
    "speed_500": 42.590444000000005,
    "speed_mile": 38.14194,
    "speed_hour": 15.071576,
    "speed_halfhour": 22.366604000000002,
    "speed_24hour": 0.0,
    "speed_alpha_racing": 42.507104000000005,
    "session_distance": 33.553898999999994,
    "username": "Tommy Gustavsson",
    "flag": "SE",
    "sexe": "Men",
    "spotname": "Brunnbybaden",
    "sessionboard": "Hiberna 4 runner,  2009",
    "sessionsail": "Sailloft Hamburg Quad 3.3,  2013",
    "sessionfin": "Custom ice blade  0",
    "sessiongpstype": "Mobile Phone App",
    "sessionurl": "https://www.gps-icesailing.com/?mnu=user&val=402432&uid=24740"
  },
  {
    "session_id": 402433,
    "session_date": "2/19/2023 12:00:00 AM",
    "event_id": 771,
    "eventname": "2022 KING OF THE ICE 2022/2023",
    "speed_avg": 43.9972232,
    "speed_2sec": 51.246692,
    "speed_10sec": 49.207640000000005,
    "speed_100": 49.61322800000001,
    "speed_250": 45.562904,
    "speed_500": 37.941924,
    "speed_mile": 32.61372,
    "speed_hour": 0.0,
    "speed_halfhour": 20.755364000000004,
    "speed_24hour": 0.0,
    "speed_alpha_racing": 37.47522,
    "session_distance": 13.030100000000001,
    "username": "Tommy Gustavsson",
    "flag": "SE",
    "sexe": "Men",
    "spotname": "Brunnbybaden",
    "sessionboard": "Hiberna 4 runner,  2009",
    "sessionsail": "Sailloft Hamburg Quad 3.3,  2013",
    "sessionfin": "Custom ice blade  0",
    "sessiongpstype": "Mobile Phone App",
    "sessionurl": "https://www.gps-icesailing.com/?mnu=user&val=402433&uid=24740"
  },
  {
    "session_id": 402434,
    "session_date": "2/19/2023 12:00:00 AM",
    "event_id": 771,
    "eventname": "2022 KING OF THE ICE 2022/2023",
    "speed_avg": 82.21842880000001,
    "speed_2sec": 90.10720800000001,
    "speed_10sec": 88.082972,
    "speed_100": 89.74792000000001,
    "speed_250": 87.80332,
    "speed_500": 86.038364,
    "speed_mile": 57.43052000000001,
    "speed_hour": 51.444856,
    "speed_halfhour": 52.833856,
    "speed_24hour": 0.0,
    "speed_alpha_racing": 56.204496,
    "session_distance": 100.6412,
    "username": "Henrik M\u00e5rd",
    "flag": "SE",
    "sexe": "Men",
    "spotname": "Ullnasj\u00f6n",
    "sessionboard": "Custom M\u00e5rdboard 4.1,  2016",
    "sessionsail": "Neilpryde Evo 2 5.5m2 recut to 4.75m2 4.8,  2016",
    "sessionfin": "Custom ice blade  0",
    "sessiongpstype": "Locosys GW-60",
    "sessionurl": "https://www.gps-icesailing.com/?mnu=user&val=402434&uid=1468"
  },
  {
    "session_id": 402677,
    "session_date": "2/25/2023 12:00:00 AM",
    "event_id": 771,
    "eventname": "2022 KING OF THE ICE 2022/2023",
    "speed_avg": 48.55647679999999,
    "speed_2sec": 60.156664,
    "speed_10sec": 56.056336,
    "speed_100": 58.062052,
    "speed_250": 51.130016000000005,
    "speed_500": 32.426668,
    "speed_mile": 0.0,
    "speed_hour": 10.736044,
    "speed_halfhour": 14.210396000000001,
    "speed_24hour": 0.0,
    "speed_alpha_racing": 30.654304,
    "session_distance": 14.09606,
    "username": "Henrik M\u00e5rd",
    "flag": "SE",
    "sexe": "Men",
    "spotname": "Altasjon, Stockholm",
    "sessionboard": "Exocet Warp Speed,  2006",
    "sessionsail": "Tushingham Formula 10.1,  2000",
    "sessionfin": "Custom ice blade  0",
    "sessiongpstype": "Locosys GW-60",
    "sessionurl": "https://www.gps-icesailing.com/?mnu=user&val=402677&uid=1468"
  },
  {
    "session_id": 402848,
    "session_date": "3/3/2023 12:00:00 AM",
    "event_id": 771,
    "eventname": "2022 KING OF THE ICE 2022/2023",
    "speed_avg": 70.6049072,
    "speed_2sec": 76.157944,
    "speed_10sec": 73.04473200000001,
    "speed_100": 75.2838,
    "speed_250": 71.765,
    "speed_500": 66.18492400000001,
    "speed_mile": 49.589152,
    "speed_hour": 0.0,
    "speed_halfhour": 30.919140000000002,
    "speed_24hour": 0.0,
    "speed_alpha_racing": 49.98548,
    "session_distance": 23.537509999999997,
    "username": "Henrik M\u00e5rd",
    "flag": "SE",
    "sexe": "Men",
    "spotname": "Drevviken",
    "sessionboard": "Custom M\u00e5rdboard 4.1,  2016",
    "sessionsail": "Point-7 F1 sl proto 5.8,  2023",
    "sessionfin": "Custom ice blade  0",
    "sessiongpstype": "Locosys GW-60",
    "sessionurl": "https://www.gps-icesailing.com/?mnu=user&val=402848&uid=1468"
  },
  {
    "session_id": 402873,
    "session_date": "3/4/2023 12:00:00 AM",
    "event_id": 771,
    "eventname": "2022 KING OF THE ICE 2022/2023",
    "speed_avg": 88.6896872,
    "speed_2sec": 99.07274,
    "speed_10sec": 97.039244,
    "speed_100": 98.73938,
    "speed_250": 96.994796,
    "speed_500": 88.273728,
    "speed_mile": 56.702684000000005,
    "speed_hour": 31.011740000000003,
    "speed_halfhour": 38.02156,
    "speed_24hour": 0.0,
    "speed_alpha_racing": 54.16174,
    "session_distance": 105.46500999999999,
    "username": "Henrik M\u00e5rd",
    "flag": "SE",
    "sexe": "Men",
    "spotname": "Drevviken",
    "sessionboard": "Custom M\u00e5rdboard 4.1,  2016",
    "sessionsail": "Point-7 F1 sl proto 4.5,  2023",
    "sessionfin": "Custom ice blade  0",
    "sessiongpstype": "Locosys GW-60",
    "sessionurl": "https://www.gps-icesailing.com/?mnu=user&val=402873&uid=1468"
  },
  {
    "session_id": 402891,
    "session_date": "3/4/2023 12:00:00 AM",
    "event_id": 771,
    "eventname": "2022 KING OF THE ICE 2022/2023",
    "speed_avg": 78.0918024,
    "speed_2sec": 82.295472,
    "speed_10sec": 79.04150800000001,
    "speed_100": 81.45281200000001,
    "speed_250": 78.537764,
    "speed_500": 75.276392,
    "speed_mile": 56.248944,
    "speed_hour": 28.305968000000004,
    "speed_halfhour": 36.602928,
    "speed_24hour": 0.0,
    "speed_alpha_racing": 52.306036,
    "session_distance": 80.79051,
    "username": "Tobias Bodin",
    "flag": "SE",
    "sexe": "Men",
    "spotname": "Drevviken",
    "sessionboard": "Custom Sharp4,  2012",
    "sessionsail": "Maui Sails TR3 4.7,  2007",
    "sessionfin": "Custom ice blade  0",
    "sessiongpstype": "Locosys GT-31",
    "sessionurl": "https://www.gps-icesailing.com/?mnu=user&val=402891&uid=5893"
  }
]